protonox/__init__.py
protonox/__main__.py
tests/__init__.py
tests/test_app_windows.py
tests/test_framework_structure.py
tests/test_kivy_compatibility.py
protonox-1.0.0.dist-info/METADATA
protonox-1.0.0.dist-info/WHEEL
protonox-1.0.0.dist-info/entry_points.txt
protonox-1.0.0.dist-info/top_level.txt
protonox-1.0.0.dist-info/RECORD
