Metadata-Version: 2.1
Name: protonox
Version: 1.0.0
Summary: Normalized Protonox Kivy toolchain, templates, and build utilities
Home-page: https://github.com/ProtonoxDEV/Protonox-Kivy-Multiplatform-Framework
Author: Juan David Morales - Protonox
Author-email: protonox@example.com
Keywords: kivy,android,buildozer,python-for-android,pyjnius,cross-platform
Classifier: Development Status :: 3 - Alpha
Classifier: Intended Audience :: Developers
Classifier: License :: OSI Approved :: MIT License
Classifier: Programming Language :: Python :: 3
Classifier: Programming Language :: Python :: 3.10
Classifier: Programming Language :: Python :: 3.11
Classifier: Programming Language :: Python :: 3.12
Classifier: Programming Language :: Python :: 3.13
Classifier: Programming Language :: Python :: 3.14
Classifier: Operating System :: OS Independent
Requires-Dist: buildozer >=1.5.0
Requires-Dist: cython <=3.3.0,>=3.0.0
Requires-Dist: kivy >=2.3.0
Requires-Dist: requests >=2.31.0
Requires-Dist: setuptools >=65.0.0
Requires-Dist: wheel >=0.40.0
